place/__init__.py
place/tools/__init__.py
place/tools/place_api_tool.py
place/tools/utils.py
place/yamls/place_api_tool.yaml
tests/__init__.py
tests/test_place_api_tool.py
place_intelligence_prompt_flow-0.0.3.dist-info/METADATA
place_intelligence_prompt_flow-0.0.3.dist-info/WHEEL
place_intelligence_prompt_flow-0.0.3.dist-info/entry_points.txt
place_intelligence_prompt_flow-0.0.3.dist-info/top_level.txt
place_intelligence_prompt_flow-0.0.3.dist-info/RECORD
