Metadata-Version: 2.1
Name: place_intelligence_prompt_flow
Version: 0.0.3
Summary: This is Place Intelligence prompt flow
